pyjmad
