Metadata-Version: 1.0
Name: pyjmad
Version: 0.0.11
Summary: A Python wrapping of JMad
Home-page: https://github.com/pymad/pyjmad
Author: Michi Hostettler
Author-email: michi.hostettler@cern.ch
License: UNKNOWN
Platform: UNKNOWN
